print_extended/__init__.py
python_print_extended-0.1.1.dist-info/LICENSE
python_print_extended-0.1.1.dist-info/METADATA
python_print_extended-0.1.1.dist-info/WHEEL
python_print_extended-0.1.1.dist-info/top_level.txt
python_print_extended-0.1.1.dist-info/RECORD
