Metadata-Version: 2.1
Name: python-print-extended
Version: 0.1.1
Summary: Beginner-friendly pretty printing
Home-page: https://github.com/spenserblack/python-print-extended
License: MIT
Project-URL: Bug Tracker, https://github.com/spenserblack/python-print-extended/issues
Keywords: print,beginner,console,pretty
Classifier: Programming Language :: Python :: 3
Classifier: Programming Language :: Python :: 3.7
Requires-Python: >=3.7
License-File: LICENSE
Requires-Dist: sty (<2,>=1)
